[
    {
        "id": 201010,
        "title": "在京东买到了 iPhone 6 疑似翻新机",
        "url": "http://www.v2ex.com/t/201010",
        "content": "昨天收到的。 \r\n1. 手机头部屏幕面板 和 金属边框里面是黑色的，都是灰。 \r\n2. 屏幕两边边缘和右下角按起来噼里啪啦响。 \r\n3. 屏幕两边按下去浮动很大，能明显感觉到，屏幕都要快掉了的感觉。 \r\n\r\n\r\nhttp://ww1.sinaimg.cn/mw690/642a7f93gw1etg5zs7uyqj20f00fkjrl.jpg\r\n\r\nhttp://ww3.sinaimg.cn/mw690/642a7f93gw1etg5zrsevmj20k00zkdh6.jpg\r\n\r\nhttp://ww1.sinaimg.cn/mw690/642a7f93gw1etg5zrdnldj20k00zkmy6.jpg\r\n\r\n已经到电话苹果售后问过了。这是不正常的现象。怀疑为翻新机或者是别人用过的。 \r\n因为还在三包的7天退货，14天换货期限内，所以建议我先找京东协商换货。",
        "content_rendered": "昨天收到的。 \r<br />1. 手机头部屏幕面板 和 金属边框里面是黑色的，都是灰。 \r<br />2. 屏幕两边边缘和右下角按起来噼里啪啦响。 \r<br />3. 屏幕两边按下去浮动很大，能明显感觉到，屏幕都要快掉了的感觉。 \r<br />\r<br />\r<br /><img src=\"http://ww1.sinaimg.cn/mw690/642a7f93gw1etg5zs7uyqj20f00fkjrl.jpg\" class=\"imgly\" style=\"max-width: 660px;\" border=\"0\" /> \r<br />\r<br /><img src=\"http://ww3.sinaimg.cn/mw690/642a7f93gw1etg5zrsevmj20k00zkdh6.jpg\" class=\"imgly\" style=\"max-width: 660px;\" border=\"0\" /> \r<br />\r<br /><img src=\"http://ww1.sinaimg.cn/mw690/642a7f93gw1etg5zrdnldj20k00zkmy6.jpg\" class=\"imgly\" style=\"max-width: 660px;\" border=\"0\" /> \r<br />\r<br />已经到电话苹果售后问过了。这是不正常的现象。怀疑为翻新机或者是别人用过的。 \r<br />因为还在三包的7天退货，14天换货期限内，所以建议我先找京东协商换货。",
        "replies": 111,
        "member": {
            "id": 8611,
            "username": "sunchuo",
            "tagline": "",
            "avatar_mini": "//cdn.v2ex.co/gravatar/2d534af8b4f3be4f90845d1e7b99c594?s=24&d=retro",
            "avatar_normal": "//cdn.v2ex.co/gravatar/2d534af8b4f3be4f90845d1e7b99c594?s=48&d=retro",
            "avatar_large": "//cdn.v2ex.co/gravatar/2d534af8b4f3be4f90845d1e7b99c594?s=73&d=retro"
        },
        "node": {
            "id": 184,
            "name": "apple",
            "title": "Apple",
            "title_alternative": "Apple",
            "url": "http://www.v2ex.com/go/apple",
            "topics": 1305,
            "avatar_mini": "//cdn.v2ex.co/navatar/6cdd/60ea/184_mini.png?m=1433239477",
            "avatar_normal": "//cdn.v2ex.co/navatar/6cdd/60ea/184_normal.png?m=1433239477",
            "avatar_large": "//cdn.v2ex.co/navatar/6cdd/60ea/184_large.png?m=1433239477"
        },
        "created": 1435201977,
        "last_modified": 1435202116,
        "last_touched": 1435249336
    },
    {
        "id": 201001,
        "title": "为何搞 python 的如此难招",
        "url": "http://www.v2ex.com/t/201001",
        "content": "帝都啊，尼玛\r\n\r\n人太难招了\r\n\r\n虽然我们是个不差钱的创业公司\r\n\r\n各个职位人刚正面的能力也都很强\r\n\r\n但是搞python人太少，人手严重不够，技术总监快要累的猝死了\r\n\r\n啊，尼玛\r\n\r\n创业好艰难\r\n\r\n为何HR不能出来刚一发，要我一个产品和技术总监一起招人\r\n\r\n要你何用。。。\r\n\r\n唉。。。\r\n\r\n心塞\r\n\r\n小伙伴们有啥建设性意见不\r\n\r\n哎嘛",
        "content_rendered": "帝都啊，尼玛\r<br />\r<br />人太难招了\r<br />\r<br />虽然我们是个不差钱的创业公司\r<br />\r<br />各个职位人刚正面的能力也都很强\r<br />\r<br />但是搞python人太少，人手严重不够，技术总监快要累的猝死了\r<br />\r<br />啊，尼玛\r<br />\r<br />创业好艰难\r<br />\r<br />为何HR不能出来刚一发，要我一个产品和技术总监一起招人\r<br />\r<br />要你何用。。。\r<br />\r<br />唉。。。\r<br />\r<br />心塞\r<br />\r<br />小伙伴们有啥建设性意见不\r<br />\r<br />哎嘛",
        "replies": 84,
        "member": {
            "id": 20949,
            "username": "DaniloSam",
            "tagline": "cafe in, code out;",
            "avatar_mini": "//cdn.v2ex.co/avatar/a555/ec5f/20949_mini.png?m=1423223957",
            "avatar_normal": "//cdn.v2ex.co/avatar/a555/ec5f/20949_normal.png?m=1423223957",
            "avatar_large": "//cdn.v2ex.co/avatar/a555/ec5f/20949_large.png?m=1423223957"
        },
        "node": {
            "id": 90,
            "name": "python",
            "title": "Python",
            "title_alternative": "Python",
            "url": "http://www.v2ex.com/go/python",
            "topics": 3375,
            "avatar_mini": "//cdn.v2ex.co/navatar/8613/985e/90_mini.png?m=1435097822",
            "avatar_normal": "//cdn.v2ex.co/navatar/8613/985e/90_normal.png?m=1435097822",
            "avatar_large": "//cdn.v2ex.co/navatar/8613/985e/90_large.png?m=1435097822"
        },
        "created": 1435200643,
        "last_modified": 1435200754,
        "last_touched": 1435257115
    },
    {
        "id": 201074,
        "title": "程序员才看得懂的 T 恤",
        "url": "http://www.v2ex.com/t/201074",
        "content": "几件程序员才看得懂的T恤\r\n\r\nhttp://tshe.me/campaigns/48\r\nhttp://tshe.me/campaigns/49\r\nhttp://tshe.me/campaigns/50\r\nhttp://tshe.me/campaigns/51\r\n\r\n顺便介绍下我们的产品：T社，一个T恤众筹的平台。\r\n我们目前也在找UI设计师: http://tshe.me/jobs/design 欢迎自荐或推荐~",
        "content_rendered": "<p>几件程序员才看得懂的T恤</p>\n\n<p><a target=\"_blank\" rel=\"nofollow\" href=\"http://tshe.me/campaigns/48\">http://tshe.me/campaigns/48</a><br>\n<a target=\"_blank\" rel=\"nofollow\" href=\"http://tshe.me/campaigns/49\">http://tshe.me/campaigns/49</a><br>\n<a target=\"_blank\" rel=\"nofollow\" href=\"http://tshe.me/campaigns/50\">http://tshe.me/campaigns/50</a><br>\n<a target=\"_blank\" rel=\"nofollow\" href=\"http://tshe.me/campaigns/51\">http://tshe.me/campaigns/51</a></p>\n\n<p>顺便介绍下我们的产品：T社，一个T恤众筹的平台。<br>\n我们目前也在找UI设计师: <a target=\"_blank\" rel=\"nofollow\" href=\"http://tshe.me/jobs/design\">http://tshe.me/jobs/design</a> 欢迎自荐或推荐~</p>\n",
        "replies": 80,
        "member": {
            "id": 73892,
            "username": "citysheep",
            "tagline": "求WEB前端/UI设计 TSHE.ME",
            "avatar_mini": "//cdn.v2ex.co/avatar/9803/7088/73892_mini.png?m=1431510287",
            "avatar_normal": "//cdn.v2ex.co/avatar/9803/7088/73892_normal.png?m=1431510287",
            "avatar_large": "//cdn.v2ex.co/avatar/9803/7088/73892_large.png?m=1431510287"
        },
        "node": {
            "id": 215,
            "name": "design",
            "title": "设计",
            "title_alternative": "Design",
            "url": "http://www.v2ex.com/go/design",
            "topics": 550,
            "avatar_mini": "//cdn.v2ex.co/navatar/3b8a/6142/215_mini.png?m=1433056985",
            "avatar_normal": "//cdn.v2ex.co/navatar/3b8a/6142/215_normal.png?m=1433056985",
            "avatar_large": "//cdn.v2ex.co/navatar/3b8a/6142/215_large.png?m=1433056985"
        },
        "created": 1435213455,
        "last_modified": 1435213455,
        "last_touched": 1435257976
    },
    {
        "id": 201053,
        "title": "广东全省 15K 名次能去哪里……好迷茫……内详，真心需要帮助",
        "url": "http://www.v2ex.com/t/201053",
        "content": "公布成绩了，今年理科过分简单了，一本线理科都倒挂文科了……去年这分能在6k的样子，今年只有15K了，现在心情有点**低落**……大概想报CS和SE专业吧，看了看比较接近去年同排名的北邮SE……不过在广东长大，不太想过“秦岭淮河”（就是北方的意思了别太较真）（北京还是可以考虑）……大家还有什么推荐么，尽量是一线沿海城市吧……\r\n\r\n\r\n说明些基本信息吧，广东考生约740K，理科一本577，理科一本约52K，本人高出一本线40+一点点\r\n\r\n\r\n\r\n如果你觉得我考得不错是来装B的就别说了，每个人定位不一样，人各有志……",
        "content_rendered": "公布成绩了，今年理科过分简单了，一本线理科都倒挂文科了……去年这分能在6k的样子，今年只有15K了，现在心情有点**低落**……大概想报CS和SE专业吧，看了看比较接近去年同排名的北邮SE……不过在广东长大，不太想过“秦岭淮河”（就是北方的意思了别太较真）（北京还是可以考虑）……大家还有什么推荐么，尽量是一线沿海城市吧……\r<br />\r<br />\r<br />说明些基本信息吧，广东考生约740K，理科一本577，理科一本约52K，本人高出一本线40+一点点\r<br />\r<br />\r<br />\r<br />如果你觉得我考得不错是来装B的就别说了，每个人定位不一样，人各有志……",
        "replies": 68,
        "member": {
            "id": 109125,
            "username": "Syaoran",
            "tagline": "叆叇",
            "avatar_mini": "//cdn.v2ex.co/avatar/c0d6/540c/109125_mini.png?m=1431919123",
            "avatar_normal": "//cdn.v2ex.co/avatar/c0d6/540c/109125_normal.png?m=1431919123",
            "avatar_large": "//cdn.v2ex.co/avatar/c0d6/540c/109125_large.png?m=1431919123"
        },
        "node": {
            "id": 858,
            "name": "u",
            "title": "大学",
            "title_alternative": "U",
            "url": "http://www.v2ex.com/go/u",
            "topics": 7,
            "avatar_mini": "//cdn.v2ex.co/navatar/a67f/0968/858_mini.png?m=1435033733",
            "avatar_normal": "//cdn.v2ex.co/navatar/a67f/0968/858_normal.png?m=1435033733",
            "avatar_large": "//cdn.v2ex.co/navatar/a67f/0968/858_large.png?m=1435033733"
        },
        "created": 1435209749,
        "last_modified": 1435209749,
        "last_touched": 1435262376
    },
    {
        "id": 201064,
        "title": "民营宽带发布了，大家对这事情怎么看呢？",
        "url": "http://www.v2ex.com/t/201064",
        "content": "今天看到不少这方面的消息，一度让我想去申请一条来试试看这货怎么样？\r\n不过担心碰上之前铁桶刚开始的时候碰上的情况，也算是给自己浇了一盆冷水了。\r\n\r\n这里大家对宽带要求高，是怎么看待这事情？",
        "content_rendered": "<p>今天看到不少这方面的消息，一度让我想去申请一条来试试看这货怎么样？<br>\n不过担心碰上之前铁桶刚开始的时候碰上的情况，也算是给自己浇了一盆冷水了。</p>\n\n<p>这里大家对宽带要求高，是怎么看待这事情？</p>\n",
        "replies": 48,
        "member": {
            "id": 922,
            "username": "jimmy",
            "tagline": "",
            "avatar_mini": "//cdn.v2ex.co/avatar/ccc0/aa1b/922_mini.png?m=1334318325",
            "avatar_normal": "//cdn.v2ex.co/avatar/ccc0/aa1b/922_normal.png?m=1334318325",
            "avatar_large": "//cdn.v2ex.co/avatar/ccc0/aa1b/922_large.png?m=1334318325"
        },
        "node": {
            "id": 108,
            "name": "bb",
            "title": "宽带症候群",
            "title_alternative": "Broadband Symptom Complex",
            "url": "http://www.v2ex.com/go/bb",
            "topics": 614,
            "avatar_mini": "//cdn.v2ex.co/navatar/a3c6/5c29/108_mini.png?m=1434151947",
            "avatar_normal": "//cdn.v2ex.co/navatar/a3c6/5c29/108_normal.png?m=1434151947",
            "avatar_large": "//cdn.v2ex.co/navatar/a3c6/5c29/108_large.png?m=1434151947"
        },
        "created": 1435212097,
        "last_modified": 1435212097,
        "last_touched": 1435246661
    },
    {
        "id": 201037,
        "title": "关于最近上海电信的事，开了个群便于大家交流",
        "url": "http://www.v2ex.com/t/201037",
        "content": "435106456\r\n各位上海电信，非精品网用户，感觉近期（1个月左右）境外访问受限，网站无法打开，游戏频繁掉线，开VPN或SS都无法解决，各种丢包各种卡的，可以加群进来交流\r\n如果是觉得国内网速有问题的就不用来了\r\n我正在向电信申诉，有新的申诉资料也可以交给我\r\n\r\n我会在我已知的3个正在讨论该问题的社区发帖",
        "content_rendered": "435106456\r<br />各位上海电信，非精品网用户，感觉近期（1个月左右）境外访问受限，网站无法打开，游戏频繁掉线，开VPN或SS都无法解决，各种丢包各种卡的，可以加群进来交流\r<br />如果是觉得国内网速有问题的就不用来了\r<br />我正在向电信申诉，有新的申诉资料也可以交给我\r<br />\r<br />我会在我已知的3个正在讨论该问题的社区发帖",
        "replies": 39,
        "member": {
            "id": 123570,
            "username": "chaoskira",
            "tagline": "",
            "avatar_mini": "//cdn.v2ex.co/gravatar/2598a1d1375d44b8803dd26f440accc5?s=24&d=retro",
            "avatar_normal": "//cdn.v2ex.co/gravatar/2598a1d1375d44b8803dd26f440accc5?s=48&d=retro",
            "avatar_large": "//cdn.v2ex.co/gravatar/2598a1d1375d44b8803dd26f440accc5?s=73&d=retro"
        },
        "node": {
            "id": 108,
            "name": "bb",
            "title": "宽带症候群",
            "title_alternative": "Broadband Symptom Complex",
            "url": "http://www.v2ex.com/go/bb",
            "topics": 614,
            "avatar_mini": "//cdn.v2ex.co/navatar/a3c6/5c29/108_mini.png?m=1434151947",
            "avatar_normal": "//cdn.v2ex.co/navatar/a3c6/5c29/108_normal.png?m=1434151947",
            "avatar_large": "//cdn.v2ex.co/navatar/a3c6/5c29/108_large.png?m=1434151947"
        },
        "created": 1435207591,
        "last_modified": 1435207591,
        "last_touched": 1435268665
    },
    {
        "id": 200966,
        "title": "[南京][垂直电商]初创的团队需要前端、后端",
        "url": "http://www.v2ex.com/t/200966",
        "content": "两个星期前在这里第一次写出找技术人才的需求，当时就遇到了几位南京的技术牛人和创业路上的朋友。我觉得这里的招聘人才的水准和效率比专业的招聘网站靠谱，所以就又过来发布一次。这次写简短一些\r\n\r\n\r\n我们要做什么：\r\n我们要做垂直电商， 模式上有点像找钢网，做一个全产业链的平台。公司在天隆寺地铁站，打算搬到丰盛商会或者36氪孵化器。丰盛商会离地铁站很近，如果去36氪会提供打车报销的\r\n\r\n我们期待的创业伙伴 \r\n对于加入的小伙伴，最重要的是彼此志同道合，谈得来，能一起做事；其次是认可这个项目，有创业的激情，能自我驱动；然后就是对做「完美」的技术产品有着执着的追求 \r\n\r\n团队介绍 \r\n目前互联网团队都是全新组建的，对于团队文化、公司制度我们都可以一起讨论。 可以有好的办公环境，弹性似的上下班，下午茶，定期的运动等等....\r\n\r\n\r\n正在招募的队友 （后端Python）\r\n\r\n前端架构师 15-25K+期权\r\n前端工程师 8-15K+期权\r\n后端架构师 15-25K+期权\r\n后端工程师 8-15K+期权\r\nUI设计师    8-15K+期权\r\n有电商平台经验或者交易、支付经验者优先；对这个项目感兴趣的优秀实习生也欢迎加入我们。\r\n\r\n产品经理  工作前期需要频繁出差，到工厂和代理商那边深入了解行业，然后把需求抽象出来。有吃苦耐劳的小伙伴可以聊一下，薪水可面议。\r\n\r\n具体的要求就不写了，每家都差不多。还有一点就是我们的项目是针对传统行业的互联网项目，线下的实体公司已有1亿的流水，新成立的互联网公司如果能成功挂牌最好（券商已经参与操作，目标是17年挂牌），如果出现最差的情况平台做的不理想也是会和线下的实体公司打个包一起挂新三板的，这一点算是预期可待吧。\r\n\r\n等WEB上线后会招募IOS、Android、产品经理等角色\r\n\r\n南京的V2EXer们，如果你不安于现状，有过一丝的创业念头，希望通过行动来证明并实现自己的价值，发个邮件约个时间我们见个面聊聊吧。 \r\n\r\n真诚期待技术人才的联系：\r\nEmail： iamwushichun@gmail.com\r\nQQ：397532261",
        "content_rendered": "两个星期前在这里第一次写出找技术人才的需求，当时就遇到了几位南京的技术牛人和创业路上的朋友。我觉得这里的招聘人才的水准和效率比专业的招聘网站靠谱，所以就又过来发布一次。这次写简短一些\r<br />\r<br />\r<br />我们要做什么：\r<br />我们要做垂直电商， 模式上有点像找钢网，做一个全产业链的平台。公司在天隆寺地铁站，打算搬到丰盛商会或者36氪孵化器。丰盛商会离地铁站很近，如果去36氪会提供打车报销的\r<br />\r<br />我们期待的创业伙伴 \r<br />对于加入的小伙伴，最重要的是彼此志同道合，谈得来，能一起做事；其次是认可这个项目，有创业的激情，能自我驱动；然后就是对做「完美」的技术产品有着执着的追求 \r<br />\r<br />团队介绍 \r<br />目前互联网团队都是全新组建的，对于团队文化、公司制度我们都可以一起讨论。 可以有好的办公环境，弹性似的上下班，下午茶，定期的运动等等....\r<br />\r<br />\r<br />正在招募的队友 （后端Python）\r<br />\r<br />前端架构师 15-25K+期权\r<br />前端工程师 8-15K+期权\r<br />后端架构师 15-25K+期权\r<br />后端工程师 8-15K+期权\r<br />UI设计师    8-15K+期权\r<br />有电商平台经验或者交易、支付经验者优先；对这个项目感兴趣的优秀实习生也欢迎加入我们。\r<br />\r<br />产品经理  工作前期需要频繁出差，到工厂和代理商那边深入了解行业，然后把需求抽象出来。有吃苦耐劳的小伙伴可以聊一下，薪水可面议。\r<br />\r<br />具体的要求就不写了，每家都差不多。还有一点就是我们的项目是针对传统行业的互联网项目，线下的实体公司已有1亿的流水，新成立的互联网公司如果能成功挂牌最好（券商已经参与操作，目标是17年挂牌），如果出现最差的情况平台做的不理想也是会和线下的实体公司打个包一起挂新三板的，这一点算是预期可待吧。\r<br />\r<br />等WEB上线后会招募IOS、Android、产品经理等角色\r<br />\r<br />南京的V2EXer们，如果你不安于现状，有过一丝的创业念头，希望通过行动来证明并实现自己的价值，发个邮件约个时间我们见个面聊聊吧。 \r<br />\r<br />真诚期待技术人才的联系：\r<br />Email： <a target=\"_blank\" href=\"mailto:iamwushichun@gmail.com\">iamwushichun@gmail.com</a>\r<br />QQ：397532261",
        "replies": 37,
        "member": {
            "id": 67416,
            "username": "wushichun",
            "tagline": "",
            "avatar_mini": "//cdn.v2ex.co/avatar/d9cf/8646/67416_mini.png?m=1415931179",
            "avatar_normal": "//cdn.v2ex.co/avatar/d9cf/8646/67416_normal.png?m=1415931179",
            "avatar_large": "//cdn.v2ex.co/avatar/d9cf/8646/67416_large.png?m=1415931179"
        },
        "node": {
            "id": 43,
            "name": "jobs",
            "title": "酷工作",
            "title_alternative": "Jobs",
            "url": "http://www.v2ex.com/go/jobs",
            "topics": 10397,
            "avatar_mini": "//cdn.v2ex.co/navatar/17e6/2166/43_mini.png?m=1435035635",
            "avatar_normal": "//cdn.v2ex.co/navatar/17e6/2166/43_normal.png?m=1435035635",
            "avatar_large": "//cdn.v2ex.co/navatar/17e6/2166/43_large.png?m=1435035635"
        },
        "created": 1435191247,
        "last_modified": 1435191737,
        "last_touched": 1435243220
    },
    {
        "id": 200882,
        "title": "程序员们，你们的 iPad 都拿来干什么用",
        "url": "http://www.v2ex.com/t/200882",
        "content": "我就平时拿来看看电子书了，偶尔浏览网页，基本不用它来看剧，iPad 上那些 App 也不常用，常用的 App 都在手机上使用了。\r\n\r\n求推荐更多使用方式，不然都被荒废在那儿了。\r\n有好玩的使用方式也行，不过别说用它来给 Mac 当第二屏幕，对这个不感兴趣。",
        "content_rendered": "我就平时拿来看看电子书了，偶尔浏览网页，基本不用它来看剧，iPad 上那些 App 也不常用，常用的 App 都在手机上使用了。\r<br />\r<br />求推荐更多使用方式，不然都被荒废在那儿了。\r<br />有好玩的使用方式也行，不过别说用它来给 Mac 当第二屏幕，对这个不感兴趣。",
        "replies": 100,
        "member": {
            "id": 67019,
            "username": "Hamniba",
            "tagline": "",
            "avatar_mini": "//cdn.v2ex.co/avatar/5d0d/ee08/67019_mini.png?m=1432273490",
            "avatar_normal": "//cdn.v2ex.co/avatar/5d0d/ee08/67019_normal.png?m=1432273490",
            "avatar_large": "//cdn.v2ex.co/avatar/5d0d/ee08/67019_large.png?m=1432273490"
        },
        "node": {
            "id": 12,
            "name": "qna",
            "title": "问与答",
            "title_alternative": "Questions and Answers",
            "url": "http://www.v2ex.com/go/qna",
            "topics": 51710,
            "avatar_mini": "//cdn.v2ex.co/navatar/c20a/d4d7/12_mini.png?m=1434537173",
            "avatar_normal": "//cdn.v2ex.co/navatar/c20a/d4d7/12_normal.png?m=1434537173",
            "avatar_large": "//cdn.v2ex.co/navatar/c20a/d4d7/12_large.png?m=1434537173"
        },
        "created": 1435144551,
        "last_modified": 1435144551,
        "last_touched": 1435229441
    },
    {
        "id": 200935,
        "title": "求教本科计算机向学校",
        "url": "http://www.v2ex.com/t/200935",
        "content": "就本省情况而言，排名和以往西安电子科技大学与东华大学接近\r\n\r\n主要方向：CS/软工\r\n备选：自动化\r\n\r\n首要考虑：专业不太差\r\n其次：学校地理位置发达些\r\n最后：学校听着好些",
        "content_rendered": "就本省情况而言，排名和以往西安电子科技大学与东华大学接近\r<br />\r<br />主要方向：CS/软工\r<br />备选：自动化\r<br />\r<br />首要考虑：专业不太差\r<br />其次：学校地理位置发达些\r<br />最后：学校听着好些",
        "replies": 67,
        "member": {
            "id": 76859,
            "username": "b244183",
            "tagline": "",
            "avatar_mini": "//cdn.v2ex.co/avatar/1658/3616/76859_mini.png?m=1413110176",
            "avatar_normal": "//cdn.v2ex.co/avatar/1658/3616/76859_normal.png?m=1413110176",
            "avatar_large": "//cdn.v2ex.co/avatar/1658/3616/76859_large.png?m=1413110176"
        },
        "node": {
            "id": 858,
            "name": "u",
            "title": "大学",
            "title_alternative": "U",
            "url": "http://www.v2ex.com/go/u",
            "topics": 7,
            "avatar_mini": "//cdn.v2ex.co/navatar/a67f/0968/858_mini.png?m=1435033733",
            "avatar_normal": "//cdn.v2ex.co/navatar/a67f/0968/858_normal.png?m=1435033733",
            "avatar_large": "//cdn.v2ex.co/navatar/a67f/0968/858_large.png?m=1435033733"
        },
        "created": 1435155423,
        "last_modified": 1435211582,
        "last_touched": 1435225513
    },
    {
        "id": 200911,
        "title": "最新版 Android QQ 内 QQWifi 强制分享 wifi，取消分享需要发送申请邮件",
        "url": "http://www.v2ex.com/t/200911",
        "content": "还好没给 QQ root \r\n呵呵，",
        "content_rendered": "还好没给 QQ root \r<br />呵呵，",
        "replies": 59,
        "member": {
            "id": 73388,
            "username": "miyuki",
            "tagline": "",
            "avatar_mini": "//cdn.v2ex.co/avatar/9717/e3b5/73388_mini.png?m=1433745014",
            "avatar_normal": "//cdn.v2ex.co/avatar/9717/e3b5/73388_normal.png?m=1433745014",
            "avatar_large": "//cdn.v2ex.co/avatar/9717/e3b5/73388_large.png?m=1433745014"
        },
        "node": {
            "id": 16,
            "name": "share",
            "title": "分享发现",
            "title_alternative": "Share",
            "url": "http://www.v2ex.com/go/share",
            "topics": 15724,
            "avatar_mini": "//cdn.v2ex.co/navatar/c74d/97b0/16_mini.png?m=1434391565",
            "avatar_normal": "//cdn.v2ex.co/navatar/c74d/97b0/16_normal.png?m=1434391565",
            "avatar_large": "//cdn.v2ex.co/navatar/c74d/97b0/16_large.png?m=1434391565"
        },
        "created": 1435151598,
        "last_modified": 1435151633,
        "last_touched": 1435215946
    },
    {
        "id": 200802,
        "title": "再吐槽 linux 的版本依赖",
        "url": "http://www.v2ex.com/t/200802",
        "content": "今天早上，由于维护docker环境 ，要安装一个叫Image magick的图片处理工具，这家伙最新版本为6.9.1-6，在安装它之前需要先装delegates，即类似的第三方处理工具，由它去处理png，jpeg等等的啥东西。\r\n就是这一堆东西： http://www.imagemagick.org/download/delegates/\r\n\r\n在这个Image magick上花了接近大半天的时间，主要是configure时死活认不出libpng，但实际上已经装完了。\r\n后来实在没办法，硬是换回了旧版本6.9.1-1完事。\r\n\r\n有时候，我会想，这些源代码编译软件的存在，就是为了折磨我们吗？这版本依赖的存在，相比windows和mac的一个包搞定的，简直是坑爹得不行。\r\n\r\n遇到这样一种源代码安装，并且版本依赖非常强的软件，你们的看法是怎样的？\r\n\r\nPS：曾经遇到过一个需要源码编译的软件，它依赖的软件，相关0.0.1都编不过，从那个时候开始，遇到需要编译安装的软件，我就觉得好日子好像又到头了。\r\nPS2：不要说apt-get和yum哈，那两个家伙确实不错，但问题是很多源代码安装的软件不在那里面啊。",
        "content_rendered": "今天早上，由于维护docker环境 ，要安装一个叫Image magick的图片处理工具，这家伙最新版本为6.9.1-6，在安装它之前需要先装delegates，即类似的第三方处理工具，由它去处理png，jpeg等等的啥东西。\r<br />就是这一堆东西： <a target=\"_blank\" href=\"http://www.imagemagick.org/download/delegates/\" rel=\"nofollow\">http://www.imagemagick.org/download/delegates/</a>\r<br />\r<br />在这个Image magick上花了接近大半天的时间，主要是configure时死活认不出libpng，但实际上已经装完了。\r<br />后来实在没办法，硬是换回了旧版本6.9.1-1完事。\r<br />\r<br />有时候，我会想，这些源代码编译软件的存在，就是为了折磨我们吗？这版本依赖的存在，相比windows和mac的一个包搞定的，简直是坑爹得不行。\r<br />\r<br />遇到这样一种源代码安装，并且版本依赖非常强的软件，你们的看法是怎样的？\r<br />\r<br />PS：曾经遇到过一个需要源码编译的软件，它依赖的软件，相关0.0.1都编不过，从那个时候开始，遇到需要编译安装的软件，我就觉得好日子好像又到头了。\r<br />PS2：不要说apt-get和yum哈，那两个家伙确实不错，但问题是很多源代码安装的软件不在那里面啊。",
        "replies": 90,
        "member": {
            "id": 32044,
            "username": "cxshun",
            "tagline": "",
            "avatar_mini": "//cdn.v2ex.co/avatar/4b75/1bc7/32044_mini.png?m=1369031007",
            "avatar_normal": "//cdn.v2ex.co/avatar/4b75/1bc7/32044_normal.png?m=1369031007",
            "avatar_large": "//cdn.v2ex.co/avatar/4b75/1bc7/32044_large.png?m=1369031007"
        },
        "node": {
            "id": 300,
            "name": "programmer",
            "title": "程序员",
            "title_alternative": "Programmer",
            "url": "http://www.v2ex.com/go/programmer",
            "topics": 8243,
            "avatar_mini": "//cdn.v2ex.co/navatar/94f6/d7e0/300_mini.png?m=1435097597",
            "avatar_normal": "//cdn.v2ex.co/navatar/94f6/d7e0/300_normal.png?m=1435097597",
            "avatar_large": "//cdn.v2ex.co/navatar/94f6/d7e0/300_large.png?m=1435097597"
        },
        "created": 1435128808,
        "last_modified": 1435128808,
        "last_touched": 1435208285
    },
    {
        "id": 200835,
        "title": "求开发一个这样的 python 程序，得多少钱？",
        "url": "http://www.v2ex.com/t/200835",
        "content": "###程序需求：\r\n  一个web服务器，可以承受的流量大概每天1000-5000次访问。\r\n  此程序可以绑定任意域名，每个域名对应不同的数据库（最好是sqlite这样的数据库，每个<10000条记录）,程序只需要读取每条数据，然后根据标题和内容生成对应的网页即可。（不需要增删查操作，数据库已经生成好的。）\r\n  批量删除域名及对应的数据库。\r\n\r\n我可以迅速的添加一个域名指向程序所在VPS的IP，然后在后台添加这个域名，指向对应的数据库，即可在浏览器中打开这个域名，生成一个网站。\r\n\r\n可以不用Python开发，用其它语言开发也行，我想着用Python开发的原因是因为我了解Python, 我希望能不装nginx,mysql，在VPS上直接运行，毕竟都是一些小网站。\r\n\r\n问下这个开发难度，愿意出钱请人开发。",
        "content_rendered": "<h3>程序需求：</h3>\n\n<p>一个web服务器，可以承受的流量大概每天1000-5000次访问。<br>\n  此程序可以绑定任意域名，每个域名对应不同的数据库（最好是sqlite这样的数据库，每个&lt;10000条记录）,程序只需要读取每条数据，然后根据标题和内容生成对应的网页即可。（不需要增删查操作，数据库已经生成好的。）<br>\n  批量删除域名及对应的数据库。</p>\n\n<p>我可以迅速的添加一个域名指向程序所在VPS的IP，然后在后台添加这个域名，指向对应的数据库，即可在浏览器中打开这个域名，生成一个网站。</p>\n\n<p>可以不用Python开发，用其它语言开发也行，我想着用Python开发的原因是因为我了解Python, 我希望能不装nginx,mysql，在VPS上直接运行，毕竟都是一些小网站。</p>\n\n<p>问下这个开发难度，愿意出钱请人开发。</p>\n",
        "replies": 77,
        "member": {
            "id": 55353,
            "username": "sbmzhcn",
            "tagline": "",
            "avatar_mini": "//cdn.v2ex.co/gravatar/261887d3640afd377efb7c6c713b70ee?s=24&d=retro",
            "avatar_normal": "//cdn.v2ex.co/gravatar/261887d3640afd377efb7c6c713b70ee?s=48&d=retro",
            "avatar_large": "//cdn.v2ex.co/gravatar/261887d3640afd377efb7c6c713b70ee?s=73&d=retro"
        },
        "node": {
            "id": 90,
            "name": "python",
            "title": "Python",
            "title_alternative": "Python",
            "url": "http://www.v2ex.com/go/python",
            "topics": 3365,
            "avatar_mini": "//cdn.v2ex.co/navatar/8613/985e/90_mini.png?m=1435097822",
            "avatar_normal": "//cdn.v2ex.co/navatar/8613/985e/90_normal.png?m=1435097822",
            "avatar_large": "//cdn.v2ex.co/navatar/8613/985e/90_large.png?m=1435097822"
        },
        "created": 1435135154,
        "last_modified": 1435135213,
        "last_touched": 1435207858
    },
    {
        "id": 200836,
        "title": "你吃过山水牛嘛？",
        "url": "http://www.v2ex.com/t/200836",
        "content": "http://i1.tietuku.com/e918e39596fe6429.jpg\r\n今天下雨去野地里抓了点，准备晚上吃。\r\n不过多数是公的，母的有卵才好吃！\r\n村里有人收购，母的1块5一只，感觉好贵。\r\n小时候多的，1、200只好抓。",
        "content_rendered": "<a target=\"_blank\" href=\"http://i1.tietuku.com/e918e39596fe6429.jpg\" rel=\"nofollow\">http://i1.tietuku.com/e918e39596fe6429.jpg</a>\r<br />今天下雨去野地里抓了点，准备晚上吃。\r<br />不过多数是公的，母的有卵才好吃！\r<br />村里有人收购，母的1块5一只，感觉好贵。\r<br />小时候多的，1、200只好抓。",
        "replies": 75,
        "member": {
            "id": 12720,
            "username": "pimin",
            "tagline": "",
            "avatar_mini": "//cdn.v2ex.co/avatar/12ae/3f82/12720_mini.png?m=1406854963",
            "avatar_normal": "//cdn.v2ex.co/avatar/12ae/3f82/12720_normal.png?m=1406854963",
            "avatar_large": "//cdn.v2ex.co/avatar/12ae/3f82/12720_large.png?m=1406854963"
        },
        "node": {
            "id": 12,
            "name": "qna",
            "title": "问与答",
            "title_alternative": "Questions and Answers",
            "url": "http://www.v2ex.com/go/qna",
            "topics": 51679,
            "avatar_mini": "//cdn.v2ex.co/navatar/c20a/d4d7/12_mini.png?m=1434537173",
            "avatar_normal": "//cdn.v2ex.co/navatar/c20a/d4d7/12_normal.png?m=1434537173",
            "avatar_large": "//cdn.v2ex.co/navatar/c20a/d4d7/12_large.png?m=1434537173"
        },
        "created": 1435135154,
        "last_modified": 1435135229,
        "last_touched": 1435206780
    },
    {
        "id": 200832,
        "title": "发现域名后面加个‘.’ 也能访问，为什么？ https://v2ex.com./",
        "url": "http://www.v2ex.com/t/200832",
        "content": "",
        "content_rendered": "",
        "replies": 59,
        "member": {
            "id": 84050,
            "username": "tcp",
            "tagline": "",
            "avatar_mini": "//cdn.v2ex.co/avatar/c4f6/4b47/84050_mini.png?m=1435162264",
            "avatar_normal": "//cdn.v2ex.co/avatar/c4f6/4b47/84050_normal.png?m=1435162264",
            "avatar_large": "//cdn.v2ex.co/avatar/c4f6/4b47/84050_large.png?m=1435162264"
        },
        "node": {
            "id": 12,
            "name": "qna",
            "title": "问与答",
            "title_alternative": "Questions and Answers",
            "url": "http://www.v2ex.com/go/qna",
            "topics": 51679,
            "avatar_mini": "//cdn.v2ex.co/navatar/c20a/d4d7/12_mini.png?m=1434537173",
            "avatar_normal": "//cdn.v2ex.co/navatar/c20a/d4d7/12_normal.png?m=1434537173",
            "avatar_large": "//cdn.v2ex.co/navatar/c20a/d4d7/12_large.png?m=1434537173"
        },
        "created": 1435134722,
        "last_modified": 1435141852,
        "last_touched": 1435207480
    },
    {
        "id": 200803,
        "title": "程序员应该如何利用上下班交通工具上的时间？",
        "url": "http://www.v2ex.com/t/200803",
        "content": "我上下班一共要3个小时的时间。\r\n大家在什么城市用什么方式上班花多长时间啊。",
        "content_rendered": "我上下班一共要3个小时的时间。\r<br />大家在什么城市用什么方式上班花多长时间啊。",
        "replies": 49,
        "member": {
            "id": 96624,
            "username": "lijianying10",
            "tagline": "",
            "avatar_mini": "//cdn.v2ex.co/gravatar/308c3d383ab316f2033bc1106c134a9c?s=24&d=retro",
            "avatar_normal": "//cdn.v2ex.co/gravatar/308c3d383ab316f2033bc1106c134a9c?s=48&d=retro",
            "avatar_large": "//cdn.v2ex.co/gravatar/308c3d383ab316f2033bc1106c134a9c?s=73&d=retro"
        },
        "node": {
            "id": 12,
            "name": "qna",
            "title": "问与答",
            "title_alternative": "Questions and Answers",
            "url": "http://www.v2ex.com/go/qna",
            "topics": 51679,
            "avatar_mini": "//cdn.v2ex.co/navatar/c20a/d4d7/12_mini.png?m=1434537173",
            "avatar_normal": "//cdn.v2ex.co/navatar/c20a/d4d7/12_normal.png?m=1434537173",
            "avatar_large": "//cdn.v2ex.co/navatar/c20a/d4d7/12_large.png?m=1434537173"
        },
        "created": 1435128855,
        "last_modified": 1435129067,
        "last_touched": 1435208244
    }
]